Workbook

Sheet company data
A1: financial year | B1: Kind of packing | C1: type of container | D1: terms of delivery | E1: terms of payment
A2: 25-26 | B2: Wooden Crate Packing | C2: FCL | D2: FOB | E2: 30 % Advance, Remaning Against Document within 7
B3: Loose packing | D3: CIF | E3: 100 % Advance
B4: American Standard | D4: CNF | E4: 70 % Advance, Remaning Against Document
E5: 100% Against Documents
E6: LC at Sight
E7: 30% Advance and Remaining Against BL within 7 days

Sheet input data
A1: Financial Year | B1: 25-26
A2: No. | B2: 02
A3: Invoice Number | B3: ="BK0" & B2 & "/" & B1 -> BK002/25-26
A4: Date | B4: 45945
A5: Proforma Invoice | B5: PI1908/25-26
A6: LUT No: | B6: =IF(B1="24-25","AD240424008317F",IF(B1="23-24","AD240322004861M",IF(B1="25-26","AD240725023182F",IF(B1="","select the financial year")))) -> AD240725023182F
A7: CONSIGNEE | B7: ZHIÑIN MENDIETA ROSA LOURDES RUC: 0105370399001 DIRECCIÓN: Barrio: HUISHIL ALTO Calle: 1 DE SEPTIEMBRE Número: S/N Intersección: BUENA ESPERANZA Referencia: DIAGONAL A LA HOSTERIA CABALLO CAMPANA Cuenca - Ecuador
A8: Party Name | B8: DAPSE EXPRESS INTERNATIONAL LOGISTICS AND TRADE RUC 172011272001 operaciones@dapseexpress.com Teléfono: 0987681580 QUITO-ECUADOR
A14: number of containers | B14: 1
A15: Kind of Packing | B15: Wooden Crate Packing
A16: Type of container | B16: FCL
A17: Terms of delivery | B17: FOB
A18: Terms of payment | B18: 30% Advance and Remaining Against BL within 7 days
A19: Place Of Receipt By Pre-Carrier | B19: MUNDRA
A20: Port Of Loading | B20: MUNDRA
A21: Port Of Discharge | B21: GUAYAQUIL
A22: Place Of Delivery | B22: GUAYAQUIL
A23: Country Of Final Destination | B23: ECUADOR
A24: Container No. | B24: MSDU1249256
A25: TOTAL SLABS | B25: 276
A26: Poduct Name 1 | B26: Polished Granite Slabs
A27: Quantity 1 | B27: 155.75
A28: Rate quantity 1 | B28: 16.2
A29: Poduct Name 2 | B29: Polished Granite Slabs
A30: Quantity 2 | B30: 168
A31: Rate quantity 2 | B31: 14.9
A32: Poduct Name 3 | B32: Polished Granite Slabs
A33: Quantity 3 | B33: 159.25
A34: Rate quantity 3 | B34: 23.2

Sheet Invoice rockstone
A1: INVOICE
A3: EXPORTER | E3: INVOICE NO. | H3: DATE
A4: BK ROCKSTONE PRIVATE LIMITED | E4: ='input data'!B3 -> BK002/25-26 | H4: ='input data'!B4 -> 45945
A5: 90/3, NR. BRAMBHANI ICE FACTORY, NR. RADHIKA SOCIETY, JASHODANAGAR CANAL ROAD, CTM CHAR RASTA, AHMEDABAD, AHMEDABAD, GUJARAT, 380026. Website: www.bkrockstone.com Email: info@bkrockstone.com Contact No: +919537651265, +919265280144 | E5: PROFORMA INVOICE | H5: LUT/ARN NO.
E6: ='input data'!B5 -> PI1908/25-26 | H6: ='input data'!B6 -> AD240725023182F
E7: PAN NO. /IEC CODE | H7: GSTIN
E8: AANCB5070H | H8: 24AANCB5070H1ZO
E9: KIND OF PACKING | H9: TYPE OF CONTAINER
E10: ='input data'!B15 -> Wooden Crate Packing | H10: ='input data'!B14 & " " & 'input data'!B16 -> 1 FCL
E11: TERMS OF DELIVERY | H11: TERMS OF PAYMENT
E12: ='input data'!B17 -> FOB | H12: ='input data'!B18 -> 30% Advance and Remaining Against BL within 7 days
A14: CONSIGNEE | E14: NOTIFY PARTY
A15: ='input data'!B7 -> ZHIÑIN MENDIETA ROSA LOURDES RUC: 0105370399001 DIRECCIÓN: Barrio: HUISHIL ALTO Calle: 1 DE SEPTIEMBRE Número: S/N Intersección: BUENA ESPERANZA Referencia: DIAGONAL A LA HOSTERIA CABALLO CAMPANA Cuenca - Ecuador
A21: Per Carriage By | C21: Place Of Receipt By Pre-Carrier | E21: Country Of Origin Of Goods | H21: Country Of Final Destination
A22: By Road Truck No. | C22: ='input data'!B19 -> MUNDRA | E22: INDIA | H22: ='input data'!B23 -> ECUADOR
A24: Vessel/ Flight No. | C24: Port Of Loading | E24: Port Of Discharge | H24: Place Of Delivery
C25: ='input data'!B20 -> MUNDRA | E25: ='input data'!B21 -> GUAYAQUIL | H25: ='input data'!B22 -> GUAYAQUIL
A26: Sr. No. | B26: Description Of Goods | F26: Quantity in | H26: Rate Per | I26: TOTAL AMOUNT
F27: SQM | H27: SQM | I27: (IN USD)
A28: 1 | B28: Black Forest Granite Slabs (Polished) Size: 2.50 Length X 0.70 Height, Thickness : 18 mm | F28: ='input data'!B27 -> 155.75 | H28: ='input data'!B28 -> 16.2 | I28: =F28*H28 -> 2523.15
A29: 2 | B29: P White Granite Slabs (Polished) Size: 2.50 Length X 0.70 Height, Thickness : 18 mm | F29: ='input data'!B30 -> 168 | H29: ='input data'!B31 -> 14.9 | I29: =F29*H29 -> 2503.2
A30: 3 | B30: Alaska White Granite Slabs (Polished) Size: 2.50 Length X 0.70 Height, Thickness : 18 mm | F30: ='input data'!B33 -> 159.25 | H30: ='input data'!B34 -> 23.2 | I30: =F30*H30 -> 3694.6
A31: Container No. | C31: Slabs | D31: Gross Weight | E31: Net Weight
A32: =UPPER('input data'!B24) -> MSDU1249256 | C32: ='input data'!B25 -> 276 | D32: 27500 kgs | E32: 27000 kgs
A34: Amount in Words: | I34: =SUM(I28:J33) -> 8720.95
A35: Eight Thousand Seven Hundred Twenty Dollars and Ninety Five Cents
A36: Bank Details
A37: ACCOUNT NAME : BK ROCKSTONE PVT LTD | E37: SWIFT CODE : BARBINBBVAT
A38: BANK NAME : BANK OF BARODA | E38: IFSC CODE : BARBOMANEAS (fifth digit zero)
A39: ACCOUNT NUMBER : 14970200000778 | E39: BRANCH : MANINAGAR (EAST)
A40: Declaration | E40: For BK ROCKSTONE PRIVATE LIMITED
A41: * We declare that invoice shows the actual price of the goods described and that all particulars are true and correct. | E41: Director
A43: * Thickness Variation will be -/+1mm.
E44: Authorised Signatory

Sheet Peacking List
A1: PACKING LIST
A2: EXPORTER | G2: INVOICE NO. | I2: DATE
A3: BK ROCKSTONE PRIVATE LIMITED | G3: ='input data'!B3 -> BK002/25-26 | I3: ='input data'!B4 -> 45945
A4: 90/3, NR. BRAMBHANI ICE FACTORY, NR. RADHIKA SOCIETY, JASHODANAGAR CANAL ROAD, CTM CHAR RASTA, AHMEDABAD, AHMEDABAD, GUJARAT, 380026. Email: info@bkrockstone.com Website: www.bkrockstone.com GST: 24AANCB5070H1ZO Contact No: +919537651265, +91926580144 | G4: LUT/ARN NO.
G5: ='input data'!B6 -> AD240725023182F
G7: OTHER REFERENCE(S)
G8: IE CODE : AANCB5070H
G9: PAN NO. : AANCB5070H
A11: CONSIGNEE | G11: NOTIFY PARTY
A12: ='input data'!B7 -> ZHIÑIN MENDIETA ROSA LOURDES RUC: 0105370399001 DIRECCIÓN: Barrio: HUISHIL ALTO Calle: 1 DE SEPTIEMBRE Número: S/N Intersección: BUENA ESPERANZA Referencia: DIAGONAL A LA HOSTERIA CABALLO CAMPANA Cuenca - Ecuador
A14: Pre-Carriage by | D14: Place of Receipt by Pre-carrier | G14: Country of Origin of Goods | I14: Country of Final Destination
D15: ='input data'!B19 -> MUNDRA | G15: INDIA | I15: ='input data'!B23 -> ECUADOR
A16: Vessel/Flight No. | D16: Port Of Loading | G16: Terms of Delivery
D17: ='input data'!B19 -> MUNDRA | G17: ='input data'!B17 -> FOB
A18: Port Of Discharge | D18: Place Of Delivery | G18: Terms of Payment
A19: ='input data'!B21 -> GUAYAQUIL | D19: ='input data'!B22 -> GUAYAQUIL | G19: ='input data'!B18 -> 30% Advance and Remaining Against BL within 7 days
A22: Sr. No. | B22: Description Of Goods | I22: SQM
A23: 1 | B23: ='Invoice rockstone'!B28 -> Black Forest Granite Slabs (Polished) Size: 2.50 Length X 0.70 Height, Thickness : 18 mm | I23: ='Invoice rockstone'!F28 -> 155.75
A24: 2 | B24: ='Invoice rockstone'!B29 -> P White Granite Slabs (Polished) Size: 2.50 Length X 0.70 Height, Thickness : 18 mm | I24: ='Invoice rockstone'!F29 -> 168
A25: 3 | B25: ='Invoice rockstone'!B30 -> Alaska White Granite Slabs (Polished) Size: 2.50 Length X 0.70 Height, Thickness : 18 mm | I25: ='Invoice rockstone'!F30 -> 159.25
A26: TOTAL | I26: =SUM(I23:J25) -> 483
A28: Container No. | C28: Slabs | D28: Gross Weight | F28: Net Weight
A29: =UPPER('input data'!B24) -> MSDU1249256 | C29: ='input data'!B25 -> 276 | D29: 27500kgs | F29: 27000kgs
A31: PACKING TYPE : | C31: ='input data'!B15 -> Wooden Crate Packing
A32: QUANTITY : 1X20 FT CONTAINER
A34: DECLARATION | G34: For BK ROCKSTONE PRIVATE LIMITED
A35: * We declare that this invoice shows the actual price of the goods described and that all particulars are true and correct.
A37: * Zero rated export under LUT. | G37: Authorised Signature

Sheet PO
B1: BK ROCKSTONE PRIVATE LIMITED
B3: 90/3, NR. BRAMBHANI ICE FACTORY, NR. RADHIKA SOCIETY,
B4: JASHODANAGAR CANAL ROAD, CTM CHAR RASTA, AHMEDABAD, AHMEDABAD, GUJARAT, 380026.
B5: info@bkrockstone.com, www.bkrockstone.com , +91-9313035076, +91-926580144
B7: PURCHASE ORDER
B9: DATE: | C9: 45944
B10: REF. NO. | C10: PO02.1/25-26
B12: TO,
B13: 7 HILLS GRANIMARMO PRIVATE LIMITED
B14: KHASRA NO 884/9, PLOT NO 44,45, VILLAGE-RALAWATA, TEHSIL-KISHANGARH, Ajmer, Rajasthan, 305801 GST: 08AABCZ7282R1ZB
B16: Dear Sir/ Madam,
B18: Description | F18: RATES | H18: SQ FOOT | J18: AMOUNT
B19: Polised Granite slabs | F19: 99.76 | H19: 1808.35 | J19: =F19*H19 -> 180401
B20: Polised Granite slabs | F20: 99.99 | H20: 1676.49 | J20: =F20*H20 -> 167632.24
H21: GST 0.1% | J21: =(J19+J20)*0.001 -> 348.03323
H22: TOTAL | J22: =SUM(J19:K21) -> 348381.26
B24: GRAND TOTAL | J24: =J22 -> 348381.26
B26: OTHER DETAILS
B27: Packing | D27: WOODEN CRATE PACKING
B28: Delivery Time
B29: Port of Delivery
B30: Port of Loading | D30: MUNDRA
B31: Country of Destination
B32: Weight
B33: Invoice Address: | D33: BK ROCKSTONE PRIVATE LIMITED
D34: 90/3, NR. BRAMBHANI ICE FACTORY, NR. RADHIKA SOCIETY,
D35: JASHODANAGAR CANAL ROAD, CTM CHAR RASTA, GUJARAT, 380026.
B36: IEC NO. AANCB5070H
B37: GSTIN NO. 24AANCB5070H1ZO
B38: LUT NO: | C38: ='input data'!B6 -> AD240725023182F
B39: For BK ROCKSTONE PRIVATE LIMITED

Sheet Sheet1
B1: BK ROCKSTONE PRIVATE LIMITED
B3: 90/3, NR. BRAMBHANI ICE FACTORY, NR. RADHIKA SOCIETY,
B4: JASHODANAGAR CANAL ROAD, CTM CHAR RASTA, AHMEDABAD, AHMEDABAD, GUJARAT, 380026.
B5: info@bkrockstone.com, www.bkrockstone.com , +91-9313035076, +91-926580144
B7: PURCHASE ORDER
B9: DATE: | C9: 45945
B10: REF. NO. | C10: PO02.2/25-26
B12: TO,
B13: PARV GRANITES
B14: PRATAPPURA, BADGAON , UDAIPUR (313001) RAJASTHAN, INDIA . +91 9461402354 GST Number : 08BEYPB0212C1ZZ PARVGRANITES@GMAIL.COM
B16: Dear Sir/ Madam,
B18: Description | F18: RATES | H18: SQ FOOT | J18: AMOUNT
B19: Polised Granite slabs | F19: 153 | H19: 1714.17 | J19: =F19*H19 -> 262268.01
H20: GST 18% | J20: =(J19)*0.18 -> 47208.242
H21: TOTAL | J21: =SUM(J19:K20) -> 309476.25
B23: GRAND TOTAL | J23: =J21 -> 309476.25
B25: OTHER DETAILS
B26: Packing | D26: WOODEN CRATE PACKING
B27: Delivery Time
B28: Port of Delivery
B29: Port of Loading | D29: MUNDRA
B30: Country of Destination
B31: Weight
B32: Invoice Address: | D32: BK ROCKSTONE PRIVATE LIMITED
D33: 90/3, NR. BRAMBHANI ICE FACTORY, NR. RADHIKA SOCIETY,
D34: JASHODANAGAR CANAL ROAD, CTM CHAR RASTA, GUJARAT, 380026.
B35: IEC NO. AANCB5070H
B36: GSTIN NO. 24AANCB5070H1ZO
B37: LUT NO: | C37: ='input data'!B6 -> AD240725023182F
B38: For BK ROCKSTONE PRIVATE LIMITED

Sheet Sheet2
B1: BK ROCKSTONE PRIVATE LIMITED
B3: 90/3, NR. BRAMBHANI ICE FACTORY, NR. RADHIKA SOCIETY,
B4: JASHODANAGAR CANAL ROAD, CTM CHAR RASTA, AHMEDABAD, AHMEDABAD, GUJARAT, 380026.
B5: info@bkrockstone.com, www.bkrockstone.com , +91-9313035076, +91-926580144
B7: PURCHASE ORDER
B9: DATE: | C9: 17 September 2025
B10: REF. NO. | C10: PO01.3/25-26
B12: TO,
B13: SRI VENKATESWARA EXPORTS
B14: SY NO:88/3C1,BUDAWADA(VIL),. CHIMAKURTHY(M.D),PRAKASAM(DIST),. GSTIN:37ABYPL5026E2ZC
B16: Dear Sir/ Madam,
B18: Description | F18: RATES | H18: SQ FOOT | J18: AMOUNT
B19: Polised Granite slabs | F19: 157.12 | H19: 1190.73 | J19: =F19*H19 -> 187087.5
H20: GST 0.1% | J20: =(J19)*0.001 -> 187.0875
H21: TOTAL | J21: =SUM(J19:K20) -> 187274.59
B23: GRAND TOTAL | J23: =J21 -> 187274.59
B25: OTHER DETAILS
B26: Packing | D26: LOOSE
B27: Delivery Time
B28: Port of Delivery
B29: Port of Loading | D29: CHENNAI
B30: Country of Destination
B31: Weight
B32: Invoice Address: | D32: BK ROCKSTONE PRIVATE LIMITED
D33: 90/3, NR. BRAMBHANI ICE FACTORY, NR. RADHIKA SOCIETY,
D34: JASHODANAGAR CANAL ROAD, CTM CHAR RASTA, GUJARAT, 380026.
B35: IEC NO. AANCB5070H
B36: GSTIN NO. 24AANCB5070H1ZO
B37: LUT NO: | C37: ='input data'!B6 -> AD240725023182F
B38: For BK ROCKSTONE PRIVATE LIMITED
